natten_version_manager/__init__.py
natten_version_manager/natten_installer.py
natten_version_manager/libzip/__init__.py
natten_version_manager/libzip/core.py
natten_version_manager/libzip/type.py
natten_version_manager/libzip/type.pyi
natten_version_manager/pypi/__init__.py
natten_version_manager/pypi/core.py
natten_version_manager/running/__init__.py
natten_version_manager/running/core.py
natten_version_manager-0.0.1b18.dist-info/LICENSE
natten_version_manager-0.0.1b18.dist-info/METADATA
natten_version_manager-0.0.1b18.dist-info/WHEEL
natten_version_manager-0.0.1b18.dist-info/top_level.txt
natten_version_manager-0.0.1b18.dist-info/RECORD
